pyvizio/__init__.py
pyvizio/cli.py
pyvizio/const.py
pyvizio/helpers.py
pyvizio/version.py
pyvizio/api/__init__.py
pyvizio/api/_protocol.py
pyvizio/api/apps.py
pyvizio/api/base.py
pyvizio/api/input.py
pyvizio/api/item.py
pyvizio/api/pair.py
pyvizio/api/remote.py
pyvizio/api/settings.py
pyvizio/discovery/__init__.py
pyvizio/discovery/ssdp.py
pyvizio/discovery/zeroconf.py
pyvizio/util/__init__.py
pyvizio/util/const.py
pyvizio-0.1.64.dist-info/licenses/LICENSE
pyvizio-0.1.64.dist-info/METADATA
pyvizio-0.1.64.dist-info/WHEEL
pyvizio-0.1.64.dist-info/entry_points.txt
pyvizio-0.1.64.dist-info/top_level.txt
pyvizio-0.1.64.dist-info/RECORD
