Metadata-Version: 2.4
Name: pyvizio
Version: 0.1.64
Summary: Python library for interfacing with Vizio SmartCast TVs and Sound Bars (2016+ models)
Author-email: Vlad Korniev <vladimir.kornev@gmail.com>
License-Expression: GPL-3.0-only
Project-URL: Homepage, https://github.com/vkorn/pyvizio
Project-URL: Repository, https://github.com/vkorn/pyvizio
Keywords: vizio,smartcast
Classifier: Development Status :: 4 - Beta
Classifier: Intended Audience :: Developers
Classifier: Programming Language :: Python :: 3.8
Classifier: Programming Language :: Python :: 3.9
Classifier: Programming Language :: Python :: 3.10
Classifier: Programming Language :: Python :: 3.11
Classifier: Programming Language :: Python :: 3.12
Classifier: Programming Language :: Python :: 3.13
Requires-Python: >=3.8
License-File: LICENSE
Requires-Dist: aiohttp
Requires-Dist: click
Requires-Dist: jsonpickle
Requires-Dist: requests
Requires-Dist: tabulate>=0.8.6
Requires-Dist: xmltodict
Requires-Dist: zeroconf>=0.24.4
Dynamic: license-file
